pyfortified_logging/__init__.py
pyfortified_logging/logger_adapter_custom.py
pyfortified_logging/logger_json_lexer.py
pyfortified_logging/logging.py
pyfortified_logging/logging_format.py
pyfortified_logging/logging_json_formatter.py
pyfortified_logging/logging_levels.py
pyfortified_logging/logging_output.py
pyfortified_logging/errors/__init__.py
pyfortified_logging/errors/errors_traceback.py
pyfortified_logging/support/__init__.py
pyfortified_logging/support/singleton.py
pyfortified_logging-0.2.1.dist-info/METADATA
pyfortified_logging-0.2.1.dist-info/RECORD
pyfortified_logging-0.2.1.dist-info/WHEEL
pyfortified_logging-0.2.1.dist-info/top_level.txt
