Metadata-Version: 2.1
Name: pyfortified-logging
Version: 0.2.1
Summary: Extension to Python `logging` functionality.
Home-page: https://github.com/jeff00seattle/pyfortified-logging
Author: UNKNOWN
Author-email: UNKNOWN
License: MIT License
Download-URL: https://github.com/jeff00seattle/pyfortified-logging/archive/v0.2.1.tar.gz
Keywords: pyfortified logging
Platform: UNKNOWN
Classifier: Development Status :: 3 - Alpha
Classifier: Intended Audience :: Developers
Classifier: Natural Language :: English
Classifier: License :: OSI Approved :: MIT License
Classifier: Operating System :: OS Independent
Classifier: Natural Language :: English
Classifier: Programming Language :: Python
Classifier: Programming Language :: Python :: 3
Classifier: Programming Language :: Python :: 3.4
Classifier: Programming Language :: Python :: 3.5
Classifier: Programming Language :: Python :: 3.6
Classifier: Topic :: Software Development :: Libraries :: Python Modules
Requires-Dist: coloredlogs (>=7.3)
Requires-Dist: python-json-logger (>=0.1.8)
Requires-Dist: pprintpp (>=0.3.0)
Requires-Dist: Pygments (>=2.2.0)
Requires-Dist: pytz (>=2018.4)
Requires-Dist: tzlocal (>=1.5.1)
